{
  "username": "neha.baby221",
  "profile_id": "64757408177",
  "full_name": "",
  "bio": "Mumbai \ud83d\udc9f\ud83d\udc95\nTelegram link \ud83d\udd17 here\ud83d\udc47\ud83d\udc8b",
  "followers_count": 51,
  "following_count": 155,
  "bio_links": [
    {
      "title": "",
      "lynx_url": "https://l.instagram.com/?u=https%3A%2F%2Ft.me%2FMilibaby600&e=AT3Vc2CBS-XBo6oJ5ENbl1MwWuU_mZ-cwKZ2qVnh7b_ovOc6oO5jShCV9IomBWDymSmsIUf_czSCT8h1JC6-Az-XJPBN3bS4",
      "url": "https://t.me/Milibaby600",
      "link_type": "external"
    }
  ],
  "profile_pic_url": "https://scontent-dfw5-2.cdninstagram.com/v/t51.2885-19/439599063_3068772809926708_1857481929148394343_n.jpg?stp=dst-jpg_s150x150_tt6&efg=eyJ2ZW5jb2RlX3RhZyI6InByb2ZpbGVfcGljLmRqYW5nby41OTEuYzIifQ&_nc_ht=scontent-dfw5-2.cdninstagram.com&_nc_cat=104&_nc_oc=Q6cZ2QGWaZzVmfBEq1vD96GhZs09A0sj_rs_aSnQid1KLKknw32rq8QMiVl3MO0hEWshoGE&_nc_ohc=Xs2wuffkYJ8Q7kNvwGxpcwI&_nc_gid=rrlZ3apeqd6f3FhR2L3uNA&edm=AOQ1c0wBAAAA&ccb=7-5&oh=00_AfWucqmaq9yJ6LnuwrjIUHgWJa1RLf8_-li3eIxhWNFBFA&oe=68A946AF&_nc_sid=8b3546",
  "profile_pic_url_hd": "https://scontent-dfw5-2.cdninstagram.com/v/t51.2885-19/439599063_3068772809926708_1857481929148394343_n.jpg?stp=dst-jpg_s320x320_tt6&efg=eyJ2ZW5jb2RlX3RhZyI6InByb2ZpbGVfcGljLmRqYW5nby41OTEuYzIifQ&_nc_ht=scontent-dfw5-2.cdninstagram.com&_nc_cat=104&_nc_oc=Q6cZ2QGWaZzVmfBEq1vD96GhZs09A0sj_rs_aSnQid1KLKknw32rq8QMiVl3MO0hEWshoGE&_nc_ohc=Xs2wuffkYJ8Q7kNvwGxpcwI&_nc_gid=rrlZ3apeqd6f3FhR2L3uNA&edm=AOQ1c0wBAAAA&ccb=7-5&oh=00_AfUhDrcDLWVaM2c602NFiMcIza8f-SszOFWJ9rGmw8ZPXw&oe=68A946AF&_nc_sid=8b3546",
  "is_business_account": false,
  "is_professional_account": false,
  "is_supervision_enabled": false,
  "is_supervised_by_viewer": false,
  "is_supervised_user": false,
  "is_joined_recently": false,
  "business_email": null,
  "business_phone_number": null,
  "business_category_name": null,
  "overall_category_name": null,
  "category_enum": null,
  "category_name": null,
  "is_private": false,
  "is_verified": false,
  "pinned_channels_list_count": 0,
  "highlight_reel_count": 0,
  "video_timeline": {
    "count": 0,
    "videos": []
  },
  "related_profiles": [],
  "owner_to_timeline_media": {
    "count": 7,
    "media": [
      {
        "id": "3312271985048299167",
        "shortcode": "C33jdI8SCaf",
        "display_url": "https://scontent-dfw5-2.cdninstagram.com/v/t51.29350-15/429876955_922944116100372_6247875159752882938_n.heic?stp=dst-jpg_e35_s1080x1080_tt6&_nc_ht=scontent-dfw5-2.cdninstagram.com&_nc_cat=100&_nc_oc=Q6cZ2QGWaZzVmfBEq1vD96GhZs09A0sj_rs_aSnQid1KLKknw32rq8QMiVl3MO0hEWshoGE&_nc_ohc=J0zrNNcnAIkQ7kNvwEofZJ1&_nc_gid=rrlZ3apeqd6f3FhR2L3uNA&edm=AOQ1c0wBAAAA&ccb=7-5&oh=00_AfWZkqVr14HCmlueDAjbUMjNMfITHapctCa1GYbXkYfZDA&oe=68A95457&_nc_sid=8b3546",
        "owner": {
          "id": "64757408177",
          "username": "neha.baby221"
        },
        "is_video": false,
        "comment": 3,
        "likes": 48,
        "preview_likes": 48,
        "thumbnail": "https://scontent-dfw5-2.cdninstagram.com/v/t51.29350-15/429876955_922944116100372_6247875159752882938_n.heic?stp=dst-jpg_e35_s640x640_sh0.08_tt6&_nc_ht=scontent-dfw5-2.cdninstagram.com&_nc_cat=100&_nc_oc=Q6cZ2QGWaZzVmfBEq1vD96GhZs09A0sj_rs_aSnQid1KLKknw32rq8QMiVl3MO0hEWshoGE&_nc_ohc=J0zrNNcnAIkQ7kNvwEofZJ1&_nc_gid=rrlZ3apeqd6f3FhR2L3uNA&edm=AOQ1c0wBAAAA&ccb=7-5&oh=00_AfVPJXBW5mAAZBaRRt6OncPiWtZ_Y9u89DTDyeM-kFdHhA&oe=68A95457&_nc_sid=8b3546",
        "timestamp": 1709073611
      },
      {
        "id": "3312271915439737786",
        "shortcode": "C33jcIHScu6",
        "display_url": "https://scontent-dfw5-1.cdninstagram.com/v/t51.29350-15/430061767_2824384657710707_7534110271122802403_n.heic?stp=dst-jpg_e35_s1080x1080_tt6&_nc_ht=scontent-dfw5-1.cdninstagram.com&_nc_cat=111&_nc_oc=Q6cZ2QGWaZzVmfBEq1vD96GhZs09A0sj_rs_aSnQid1KLKknw32rq8QMiVl3MO0hEWshoGE&_nc_ohc=8wUEYg4T21oQ7kNvwGSSgEz&_nc_gid=rrlZ3apeqd6f3FhR2L3uNA&edm=AOQ1c0wBAAAA&ccb=7-5&oh=00_AfWdH5ctj-_U0P2hJXXqWRFgAl8OlF0GtIwVk8ztkXcRHw&oe=68A94C28&_nc_sid=8b3546",
        "owner": {
          "id": "64757408177",
          "username": "neha.baby221"
        },
        "is_video": false,
        "comment": 0,
        "likes": 36,
        "preview_likes": 36,
        "thumbnail": "https://scontent-dfw5-1.cdninstagram.com/v/t51.29350-15/430061767_2824384657710707_7534110271122802403_n.heic?stp=dst-jpg_e35_s640x640_sh0.08_tt6&_nc_ht=scontent-dfw5-1.cdninstagram.com&_nc_cat=111&_nc_oc=Q6cZ2QGWaZzVmfBEq1vD96GhZs09A0sj_rs_aSnQid1KLKknw32rq8QMiVl3MO0hEWshoGE&_nc_ohc=8wUEYg4T21oQ7kNvwGSSgEz&_nc_gid=rrlZ3apeqd6f3FhR2L3uNA&edm=AOQ1c0wBAAAA&ccb=7-5&oh=00_AfW3ohLmt3HOnvp0rCoDYeBjnHftI-iPRUk7aOsBVJSU8A&oe=68A94C28&_nc_sid=8b3546",
        "timestamp": 1709073603
      },
      {
        "id": "3312271807981767179",
        "shortcode": "C33jakCS0oL",
        "display_url": "https://scontent-dfw5-1.cdninstagram.com/v/t51.29350-15/430414202_222013340938367_3043023195792053093_n.heic?stp=dst-jpg_e35_tt6&_nc_ht=scontent-dfw5-1.cdninstagram.com&_nc_cat=111&_nc_oc=Q6cZ2QGWaZzVmfBEq1vD96GhZs09A0sj_rs_aSnQid1KLKknw32rq8QMiVl3MO0hEWshoGE&_nc_ohc=LBUwvbBqDegQ7kNvwGNYkEn&_nc_gid=rrlZ3apeqd6f3FhR2L3uNA&edm=AOQ1c0wBAAAA&ccb=7-5&oh=00_AfWRyQa0wHQbB8OWKcLnmnWIlk3-togyk-H5K_kV-U_-4g&oe=68A94559&_nc_sid=8b3546",
        "owner": {
          "id": "64757408177",
          "username": "neha.baby221"
        },
        "is_video": false,
        "comment": 0,
        "likes": 30,
        "preview_likes": 30,
        "thumbnail": "https://scontent-dfw5-1.cdninstagram.com/v/t51.29350-15/430414202_222013340938367_3043023195792053093_n.heic?stp=dst-jpg_e35_tt6&_nc_ht=scontent-dfw5-1.cdninstagram.com&_nc_cat=111&_nc_oc=Q6cZ2QGWaZzVmfBEq1vD96GhZs09A0sj_rs_aSnQid1KLKknw32rq8QMiVl3MO0hEWshoGE&_nc_ohc=LBUwvbBqDegQ7kNvwGNYkEn&_nc_gid=rrlZ3apeqd6f3FhR2L3uNA&edm=AOQ1c0wBAAAA&ccb=7-5&oh=00_AfWRyQa0wHQbB8OWKcLnmnWIlk3-togyk-H5K_kV-U_-4g&oe=68A94559&_nc_sid=8b3546",
        "timestamp": 1709073590
      },
      {
        "id": "3312271693250709241",
        "shortcode": "C33jY5Lykb5",
        "display_url": "https://scontent-dfw5-2.cdninstagram.com/v/t51.29350-15/430495352_1429312497725442_4988168607713469670_n.heic?stp=dst-jpg_e35_tt6&_nc_ht=scontent-dfw5-2.cdninstagram.com&_nc_cat=106&_nc_oc=Q6cZ2QGWaZzVmfBEq1vD96GhZs09A0sj_rs_aSnQid1KLKknw32rq8QMiVl3MO0hEWshoGE&_nc_ohc=wBMYRl9_HIwQ7kNvwGeonN5&_nc_gid=rrlZ3apeqd6f3FhR2L3uNA&edm=AOQ1c0wBAAAA&ccb=7-5&oh=00_AfWASXhpBHEFBWoUcHiAvtJ3pMA71HDjzvA7NW3269izUQ&oe=68A9582F&_nc_sid=8b3546",
        "owner": {
          "id": "64757408177",
          "username": "neha.baby221"
        },
        "is_video": false,
        "comment": 1,
        "likes": 37,
        "preview_likes": 37,
        "thumbnail": "https://scontent-dfw5-2.cdninstagram.com/v/t51.29350-15/430495352_1429312497725442_4988168607713469670_n.heic?stp=dst-jpg_e35_s640x640_sh0.08_tt6&_nc_ht=scontent-dfw5-2.cdninstagram.com&_nc_cat=106&_nc_oc=Q6cZ2QGWaZzVmfBEq1vD96GhZs09A0sj_rs_aSnQid1KLKknw32rq8QMiVl3MO0hEWshoGE&_nc_ohc=wBMYRl9_HIwQ7kNvwGeonN5&_nc_gid=rrlZ3apeqd6f3FhR2L3uNA&edm=AOQ1c0wBAAAA&ccb=7-5&oh=00_AfU3rYVF533DjG7ZF-V7eIBtzVd38AaivMlPTUkjAgemlw&oe=68A9582F&_nc_sid=8b3546",
        "timestamp": 1709073577
      },
      {
        "id": "3312271305134838071",
        "shortcode": "C33jTPuSBE3",
        "display_url": "https://scontent-dfw5-1.cdninstagram.com/v/t51.29350-15/430381479_322392700830413_1040491162889598067_n.heic?stp=dst-jpg_e35_tt6&_nc_ht=scontent-dfw5-1.cdninstagram.com&_nc_cat=105&_nc_oc=Q6cZ2QGWaZzVmfBEq1vD96GhZs09A0sj_rs_aSnQid1KLKknw32rq8QMiVl3MO0hEWshoGE&_nc_ohc=JjlCufv8u2oQ7kNvwGHbCED&_nc_gid=rrlZ3apeqd6f3FhR2L3uNA&edm=AOQ1c0wBAAAA&ccb=7-5&oh=00_AfUR4ijcjJ4x_-Ia-4DahTm4ZFvKtjFPlfIJ14-8tROdQg&oe=68A92C1E&_nc_sid=8b3546",
        "owner": {
          "id": "64757408177",
          "username": "neha.baby221"
        },
        "is_video": false,
        "comment": 1,
        "likes": 25,
        "preview_likes": 25,
        "thumbnail": "https://scontent-dfw5-1.cdninstagram.com/v/t51.29350-15/430381479_322392700830413_1040491162889598067_n.heic?stp=dst-jpg_e35_s640x640_sh0.08_tt6&_nc_ht=scontent-dfw5-1.cdninstagram.com&_nc_cat=105&_nc_oc=Q6cZ2QGWaZzVmfBEq1vD96GhZs09A0sj_rs_aSnQid1KLKknw32rq8QMiVl3MO0hEWshoGE&_nc_ohc=JjlCufv8u2oQ7kNvwGHbCED&_nc_gid=rrlZ3apeqd6f3FhR2L3uNA&edm=AOQ1c0wBAAAA&ccb=7-5&oh=00_AfXMgow6FTbn5t4ME0xSRPBxk5FxvrHFh04-kgzXP-1JZg&oe=68A92C1E&_nc_sid=8b3546",
        "timestamp": 1709073530
      },
      {
        "id": "3301103915317558904",
        "shortcode": "C3P4IVfJ354",
        "display_url": "https://scontent-dfw5-2.cdninstagram.com/v/t51.29350-15/426423767_936523147526150_3924645519334107472_n.heic?stp=dst-jpg_e35_tt6&_nc_ht=scontent-dfw5-2.cdninstagram.com&_nc_cat=102&_nc_oc=Q6cZ2QGWaZzVmfBEq1vD96GhZs09A0sj_rs_aSnQid1KLKknw32rq8QMiVl3MO0hEWshoGE&_nc_ohc=A7Tp6RTtyB0Q7kNvwF2t7E5&_nc_gid=rrlZ3apeqd6f3FhR2L3uNA&edm=AOQ1c0wBAAAA&ccb=7-5&oh=00_AfW0v_-gnmVIlNlcTOEEfnkVsWOWSkLdVHxZ3IseE8or7g&oe=68A94B85&_nc_sid=8b3546",
        "owner": {
          "id": "64757408177",
          "username": "neha.baby221"
        },
        "is_video": false,
        "comment": 0,
        "likes": 30,
        "preview_likes": 30,
        "thumbnail": "https://scontent-dfw5-2.cdninstagram.com/v/t51.29350-15/426423767_936523147526150_3924645519334107472_n.heic?stp=dst-jpg_e35_s640x640_sh0.08_tt6&_nc_ht=scontent-dfw5-2.cdninstagram.com&_nc_cat=102&_nc_oc=Q6cZ2QGWaZzVmfBEq1vD96GhZs09A0sj_rs_aSnQid1KLKknw32rq8QMiVl3MO0hEWshoGE&_nc_ohc=A7Tp6RTtyB0Q7kNvwF2t7E5&_nc_gid=rrlZ3apeqd6f3FhR2L3uNA&edm=AOQ1c0wBAAAA&ccb=7-5&oh=00_AfU6c98BrNfdxCIFoB9t9WGaGa10oykmJOOlTFtLR_qTuA&oe=68A94B85&_nc_sid=8b3546",
        "timestamp": 1707742274
      },
      {
        "id": "3301103803220545248",
        "shortcode": "C3P4GtFps7g",
        "display_url": "https://scontent-dfw5-2.cdninstagram.com/v/t51.29350-15/427285692_725078013101306_614930431322868177_n.heic?stp=dst-jpg_e35_tt6&_nc_ht=scontent-dfw5-2.cdninstagram.com&_nc_cat=102&_nc_oc=Q6cZ2QGWaZzVmfBEq1vD96GhZs09A0sj_rs_aSnQid1KLKknw32rq8QMiVl3MO0hEWshoGE&_nc_ohc=UdMAIENzR1sQ7kNvwHaI7Do&_nc_gid=rrlZ3apeqd6f3FhR2L3uNA&edm=AOQ1c0wBAAAA&ccb=7-5&oh=00_AfVvSepvTQ0GgLkPVHGgFSnU-4emuY2xUkzc_3UOVj8dUA&oe=68A95EED&_nc_sid=8b3546",
        "owner": {
          "id": "64757408177",
          "username": "neha.baby221"
        },
        "is_video": false,
        "comment": 2,
        "likes": 35,
        "preview_likes": 35,
        "thumbnail": "https://scontent-dfw5-2.cdninstagram.com/v/t51.29350-15/427285692_725078013101306_614930431322868177_n.heic?stp=dst-jpg_e35_tt6&_nc_ht=scontent-dfw5-2.cdninstagram.com&_nc_cat=102&_nc_oc=Q6cZ2QGWaZzVmfBEq1vD96GhZs09A0sj_rs_aSnQid1KLKknw32rq8QMiVl3MO0hEWshoGE&_nc_ohc=UdMAIENzR1sQ7kNvwHaI7Do&_nc_gid=rrlZ3apeqd6f3FhR2L3uNA&edm=AOQ1c0wBAAAA&ccb=7-5&oh=00_AfVvSepvTQ0GgLkPVHGgFSnU-4emuY2xUkzc_3UOVj8dUA&oe=68A95EED&_nc_sid=8b3546",
        "timestamp": 1707742260
      }
    ]
  },
  "account_label": "fake"
}