{
  "username": "san_geeta3762",
  "profile_id": "68248334593",
  "full_name": "",
  "bio": "",
  "followers_count": 30,
  "following_count": 165,
  "bio_links": [],
  "profile_pic_url": "https://scontent-iad3-2.cdninstagram.com/v/t51.2885-19/479898927_1166644794823626_6147017062588186437_n.jpg?stp=dst-jpg_s150x150_tt6&efg=eyJ2ZW5jb2RlX3RhZyI6InByb2ZpbGVfcGljLmRqYW5nby4xMDgwLmMyIn0&_nc_ht=scontent-iad3-2.cdninstagram.com&_nc_cat=106&_nc_oc=Q6cZ2QHxrDTszC2wSGrbX343tQ1i9t0eGw4D7zbcAV493Zd3DouZP3pp6pyipBNm47fSBF4&_nc_ohc=DTQHCOlE634Q7kNvwHAD5uj&_nc_gid=PS9vT6sOX2pCIeUUOQ6Ihg&edm=AOQ1c0wBAAAA&ccb=7-5&oh=00_AfXQ6YR8_KrjLS4qLbYW6aChr3t95MPWQOAY96BztP1E6Q&oe=68A9474D&_nc_sid=8b3546",
  "profile_pic_url_hd": "https://scontent-iad3-2.cdninstagram.com/v/t51.2885-19/479898927_1166644794823626_6147017062588186437_n.jpg?stp=dst-jpg_s320x320_tt6&efg=eyJ2ZW5jb2RlX3RhZyI6InByb2ZpbGVfcGljLmRqYW5nby4xMDgwLmMyIn0&_nc_ht=scontent-iad3-2.cdninstagram.com&_nc_cat=106&_nc_oc=Q6cZ2QHxrDTszC2wSGrbX343tQ1i9t0eGw4D7zbcAV493Zd3DouZP3pp6pyipBNm47fSBF4&_nc_ohc=DTQHCOlE634Q7kNvwHAD5uj&_nc_gid=PS9vT6sOX2pCIeUUOQ6Ihg&edm=AOQ1c0wBAAAA&ccb=7-5&oh=00_AfWAmWRr0ICBzeQL8A2fdRrplt6omX84LTNxyce-qOCUEg&oe=68A9474D&_nc_sid=8b3546",
  "is_business_account": false,
  "is_professional_account": false,
  "is_supervision_enabled": false,
  "is_supervised_by_viewer": false,
  "is_supervised_user": false,
  "is_joined_recently": false,
  "business_email": null,
  "business_phone_number": null,
  "business_category_name": null,
  "overall_category_name": null,
  "category_enum": null,
  "category_name": null,
  "is_private": false,
  "is_verified": false,
  "pinned_channels_list_count": 0,
  "highlight_reel_count": 0,
  "video_timeline": {
    "count": 0,
    "videos": []
  },
  "related_profiles": [],
  "owner_to_timeline_media": {
    "count": 0,
    "media": []
  },
  "account_label": "fake"
}