{
  "username": "ur.anuska_02",
  "profile_id": "17535406778",
  "full_name": "\ud83e\uddff",
  "bio": "",
  "followers_count": 53,
  "following_count": 755,
  "bio_links": [],
  "profile_pic_url": "https://scontent-iad3-2.cdninstagram.com/v/t51.2885-19/520369763_18098093749590779_5120172762147234761_n.jpg?stp=dst-jpg_s150x150_tt6&efg=eyJ2ZW5jb2RlX3RhZyI6InByb2ZpbGVfcGljLmRqYW5nby4xMDgwLmMyIn0&_nc_ht=scontent-iad3-2.cdninstagram.com&_nc_cat=111&_nc_oc=Q6cZ2QEXe0vNxFhpDzngf_bNlkpKqkFkdhkZsHhA51T4qyWBbMNKzC7Uf-JVU4i6wCypxkA&_nc_ohc=E2aabZliDOUQ7kNvwHoBNKE&_nc_gid=sYR9JFjAApnUbkfBNNVK_A&edm=AOQ1c0wBAAAA&ccb=7-5&oh=00_AfVuliobtSG6QqqLL-P4Y8EQV3CWH-UZc2uj3Wz2iEArTg&oe=68A95262&_nc_sid=8b3546",
  "profile_pic_url_hd": "https://scontent-iad3-2.cdninstagram.com/v/t51.2885-19/520369763_18098093749590779_5120172762147234761_n.jpg?stp=dst-jpg_s320x320_tt6&efg=eyJ2ZW5jb2RlX3RhZyI6InByb2ZpbGVfcGljLmRqYW5nby4xMDgwLmMyIn0&_nc_ht=scontent-iad3-2.cdninstagram.com&_nc_cat=111&_nc_oc=Q6cZ2QEXe0vNxFhpDzngf_bNlkpKqkFkdhkZsHhA51T4qyWBbMNKzC7Uf-JVU4i6wCypxkA&_nc_ohc=E2aabZliDOUQ7kNvwHoBNKE&_nc_gid=sYR9JFjAApnUbkfBNNVK_A&edm=AOQ1c0wBAAAA&ccb=7-5&oh=00_AfWOXWfOCpBBO8kG5EEIFEH_NURKfb9NQdJd4iQ_TSwxRw&oe=68A95262&_nc_sid=8b3546",
  "is_business_account": false,
  "is_professional_account": false,
  "is_supervision_enabled": false,
  "is_supervised_by_viewer": false,
  "is_supervised_user": false,
  "is_joined_recently": false,
  "business_email": null,
  "business_phone_number": null,
  "business_category_name": null,
  "overall_category_name": null,
  "category_enum": null,
  "category_name": null,
  "is_private": false,
  "is_verified": false,
  "pinned_channels_list_count": 0,
  "highlight_reel_count": 0,
  "video_timeline": {
    "count": 0,
    "videos": []
  },
  "related_profiles": [],
  "owner_to_timeline_media": {
    "count": 12,
    "media": [
      {
        "id": "2101892603288256621",
        "shortcode": "B0rbC-3BIBt",
        "display_url": "https://scontent-iad3-1.cdninstagram.com/v/t51.2885-15/66376126_138292364043440_7640333924396771113_n.jpg?stp=dst-jpg_e35_tt6&_nc_ht=scontent-iad3-1.cdninstagram.com&_nc_cat=108&_nc_oc=Q6cZ2QEXe0vNxFhpDzngf_bNlkpKqkFkdhkZsHhA51T4qyWBbMNKzC7Uf-JVU4i6wCypxkA&_nc_ohc=-MyEkBiGtKoQ7kNvwFhk-fd&_nc_gid=sYR9JFjAApnUbkfBNNVK_A&edm=AOQ1c0wBAAAA&ccb=7-5&oh=00_AfUE6UXPs0z29dLocImu57ywO5LT_w_191QqcD9az9DVuw&oe=68A933AD&_nc_sid=8b3546",
        "owner": {
          "id": "17535406778",
          "username": "ur.anuska_02"
        },
        "is_video": false,
        "comment": 1,
        "likes": 0,
        "preview_likes": 0,
        "thumbnail": "https://scontent-iad3-1.cdninstagram.com/v/t51.2885-15/66376126_138292364043440_7640333924396771113_n.jpg?stp=dst-jpg_e35_tt6&_nc_ht=scontent-iad3-1.cdninstagram.com&_nc_cat=108&_nc_oc=Q6cZ2QEXe0vNxFhpDzngf_bNlkpKqkFkdhkZsHhA51T4qyWBbMNKzC7Uf-JVU4i6wCypxkA&_nc_ohc=-MyEkBiGtKoQ7kNvwFhk-fd&_nc_gid=sYR9JFjAApnUbkfBNNVK_A&edm=AOQ1c0wBAAAA&ccb=7-5&oh=00_AfUE6UXPs0z29dLocImu57ywO5LT_w_191QqcD9az9DVuw&oe=68A933AD&_nc_sid=8b3546",
        "timestamp": 1564785145
      },
      {
        "id": "2101864692174919542",
        "shortcode": "B0rUs0nBZd2",
        "display_url": "https://scontent-iad3-1.cdninstagram.com/v/t51.2885-15/66125536_480379556123420_8974351232095762303_n.jpg?stp=dst-jpg_e35_tt6&_nc_ht=scontent-iad3-1.cdninstagram.com&_nc_cat=108&_nc_oc=Q6cZ2QEXe0vNxFhpDzngf_bNlkpKqkFkdhkZsHhA51T4qyWBbMNKzC7Uf-JVU4i6wCypxkA&_nc_ohc=G3chc02lxRkQ7kNvwFAV7bO&_nc_gid=sYR9JFjAApnUbkfBNNVK_A&edm=AOQ1c0wBAAAA&ccb=7-5&oh=00_AfXaf_x1Wqn89YHanKVnjmMv3ZdXR60Tb7OTjUGyDXKkxg&oe=68A92AF1&_nc_sid=8b3546",
        "owner": {
          "id": "17535406778",
          "username": "ur.anuska_02"
        },
        "is_video": false,
        "comment": 0,
        "likes": 0,
        "preview_likes": 0,
        "thumbnail": "https://scontent-iad3-1.cdninstagram.com/v/t51.2885-15/66125536_480379556123420_8974351232095762303_n.jpg?stp=dst-jpg_e35_tt6&_nc_ht=scontent-iad3-1.cdninstagram.com&_nc_cat=108&_nc_oc=Q6cZ2QEXe0vNxFhpDzngf_bNlkpKqkFkdhkZsHhA51T4qyWBbMNKzC7Uf-JVU4i6wCypxkA&_nc_ohc=G3chc02lxRkQ7kNvwFAV7bO&_nc_gid=sYR9JFjAApnUbkfBNNVK_A&edm=AOQ1c0wBAAAA&ccb=7-5&oh=00_AfXaf_x1Wqn89YHanKVnjmMv3ZdXR60Tb7OTjUGyDXKkxg&oe=68A92AF1&_nc_sid=8b3546",
        "timestamp": 1564781818
      },
      {
        "id": "2101864594632148915",
        "shortcode": "B0rUrZxBQez",
        "display_url": "https://scontent-iad3-1.cdninstagram.com/v/t51.2885-15/66025874_342095250069542_3488066981267466699_n.jpg?stp=dst-jpg_e35_tt6&_nc_ht=scontent-iad3-1.cdninstagram.com&_nc_cat=102&_nc_oc=Q6cZ2QEXe0vNxFhpDzngf_bNlkpKqkFkdhkZsHhA51T4qyWBbMNKzC7Uf-JVU4i6wCypxkA&_nc_ohc=etg5ThApH-wQ7kNvwESah4K&_nc_gid=sYR9JFjAApnUbkfBNNVK_A&edm=AOQ1c0wBAAAA&ccb=7-5&oh=00_AfU18mPwguhcU5WhgzVDNizyPkXFbn8r7r6xBdLCtDaUVw&oe=68A94439&_nc_sid=8b3546",
        "owner": {
          "id": "17535406778",
          "username": "ur.anuska_02"
        },
        "is_video": false,
        "comment": 0,
        "likes": 0,
        "preview_likes": 0,
        "thumbnail": "https://scontent-iad3-1.cdninstagram.com/v/t51.2885-15/66025874_342095250069542_3488066981267466699_n.jpg?stp=dst-jpg_e35_tt6&_nc_ht=scontent-iad3-1.cdninstagram.com&_nc_cat=102&_nc_oc=Q6cZ2QEXe0vNxFhpDzngf_bNlkpKqkFkdhkZsHhA51T4qyWBbMNKzC7Uf-JVU4i6wCypxkA&_nc_ohc=etg5ThApH-wQ7kNvwESah4K&_nc_gid=sYR9JFjAApnUbkfBNNVK_A&edm=AOQ1c0wBAAAA&ccb=7-5&oh=00_AfU18mPwguhcU5WhgzVDNizyPkXFbn8r7r6xBdLCtDaUVw&oe=68A94439&_nc_sid=8b3546",
        "timestamp": 1564781806
      },
      {
        "id": "2101830307581144610",
        "shortcode": "B0rM4ddhi4i",
        "display_url": "https://scontent-iad3-2.cdninstagram.com/v/t51.2885-15/66062779_1964518133650107_3363896552643465530_n.jpg?stp=dst-jpg_e35_tt6&_nc_ht=scontent-iad3-2.cdninstagram.com&_nc_cat=103&_nc_oc=Q6cZ2QEXe0vNxFhpDzngf_bNlkpKqkFkdhkZsHhA51T4qyWBbMNKzC7Uf-JVU4i6wCypxkA&_nc_ohc=73eGA6j1dIoQ7kNvwFcMBIz&_nc_gid=sYR9JFjAApnUbkfBNNVK_A&edm=AOQ1c0wBAAAA&ccb=7-5&oh=00_AfUrb2lALPCSo4GHJhHawk6fqPWGrQfRwtRgNvUVUWb8hw&oe=68A93298&_nc_sid=8b3546",
        "owner": {
          "id": "17535406778",
          "username": "ur.anuska_02"
        },
        "is_video": false,
        "comment": 0,
        "likes": 1,
        "preview_likes": 1,
        "thumbnail": "https://scontent-iad3-2.cdninstagram.com/v/t51.2885-15/66062779_1964518133650107_3363896552643465530_n.jpg?stp=dst-jpg_e35_tt6&_nc_ht=scontent-iad3-2.cdninstagram.com&_nc_cat=103&_nc_oc=Q6cZ2QEXe0vNxFhpDzngf_bNlkpKqkFkdhkZsHhA51T4qyWBbMNKzC7Uf-JVU4i6wCypxkA&_nc_ohc=73eGA6j1dIoQ7kNvwFcMBIz&_nc_gid=sYR9JFjAApnUbkfBNNVK_A&edm=AOQ1c0wBAAAA&ccb=7-5&oh=00_AfUrb2lALPCSo4GHJhHawk6fqPWGrQfRwtRgNvUVUWb8hw&oe=68A93298&_nc_sid=8b3546",
        "timestamp": 1564777719
      },
      {
        "id": "2101830166182755399",
        "shortcode": "B0rM2ZxhfxH",
        "display_url": "https://scontent-iad3-1.cdninstagram.com/v/t51.2885-15/65955380_137769320765443_3245430960634468282_n.jpg?stp=dst-jpg_e35_tt6&_nc_ht=scontent-iad3-1.cdninstagram.com&_nc_cat=107&_nc_oc=Q6cZ2QEXe0vNxFhpDzngf_bNlkpKqkFkdhkZsHhA51T4qyWBbMNKzC7Uf-JVU4i6wCypxkA&_nc_ohc=OGpx7sXv9JkQ7kNvwGHaWCV&_nc_gid=sYR9JFjAApnUbkfBNNVK_A&edm=AOQ1c0wBAAAA&ccb=7-5&oh=00_AfUe5T4-ei9t_1gjV-rQ2u73lG4TinzBaIuitYNFa-VuMQ&oe=68A93213&_nc_sid=8b3546",
        "owner": {
          "id": "17535406778",
          "username": "ur.anuska_02"
        },
        "is_video": false,
        "comment": 0,
        "likes": 1,
        "preview_likes": 1,
        "thumbnail": "https://scontent-iad3-1.cdninstagram.com/v/t51.2885-15/65955380_137769320765443_3245430960634468282_n.jpg?stp=dst-jpg_e35_s640x640_sh0.08_tt6&_nc_ht=scontent-iad3-1.cdninstagram.com&_nc_cat=107&_nc_oc=Q6cZ2QEXe0vNxFhpDzngf_bNlkpKqkFkdhkZsHhA51T4qyWBbMNKzC7Uf-JVU4i6wCypxkA&_nc_ohc=OGpx7sXv9JkQ7kNvwGHaWCV&_nc_gid=sYR9JFjAApnUbkfBNNVK_A&edm=AOQ1c0wBAAAA&ccb=7-5&oh=00_AfX467rZ5j2fsjpZH5FJU0xsp4AedoCt8nRY2IcChGIoTw&oe=68A93213&_nc_sid=8b3546",
        "timestamp": 1564777702
      },
      {
        "id": "2101830016420928227",
        "shortcode": "B0rM0OTBdrj",
        "display_url": "https://scontent-iad3-1.cdninstagram.com/v/t51.2885-15/66492493_932649260417503_9077080482227151142_n.jpg?stp=dst-jpg_e35_tt6&_nc_ht=scontent-iad3-1.cdninstagram.com&_nc_cat=107&_nc_oc=Q6cZ2QEXe0vNxFhpDzngf_bNlkpKqkFkdhkZsHhA51T4qyWBbMNKzC7Uf-JVU4i6wCypxkA&_nc_ohc=4br2fBn10IQQ7kNvwF6NBKm&_nc_gid=sYR9JFjAApnUbkfBNNVK_A&edm=AOQ1c0wBAAAA&ccb=7-5&oh=00_AfWnGVSIG_K11TBVUA69I9TxwLrTOWFYyY5LkBr1gyLq0g&oe=68A95030&_nc_sid=8b3546",
        "owner": {
          "id": "17535406778",
          "username": "ur.anuska_02"
        },
        "is_video": false,
        "comment": 0,
        "likes": 0,
        "preview_likes": 0,
        "thumbnail": "https://scontent-iad3-1.cdninstagram.com/v/t51.2885-15/66492493_932649260417503_9077080482227151142_n.jpg?stp=dst-jpg_e35_s640x640_sh0.08_tt6&_nc_ht=scontent-iad3-1.cdninstagram.com&_nc_cat=107&_nc_oc=Q6cZ2QEXe0vNxFhpDzngf_bNlkpKqkFkdhkZsHhA51T4qyWBbMNKzC7Uf-JVU4i6wCypxkA&_nc_ohc=4br2fBn10IQQ7kNvwF6NBKm&_nc_gid=sYR9JFjAApnUbkfBNNVK_A&edm=AOQ1c0wBAAAA&ccb=7-5&oh=00_AfW2z-OHQ0gDr4iVMB7JTqSNCGF-tpAOBg0kO36XLiqNDQ&oe=68A95030&_nc_sid=8b3546",
        "timestamp": 1564777684
      },
      {
        "id": "2101829859864325755",
        "shortcode": "B0rMx8fha57",
        "display_url": "https://scontent-iad3-2.cdninstagram.com/v/t51.2885-15/67847246_149991529415619_56392095866175809_n.jpg?stp=dst-jpg_e35_tt6&_nc_ht=scontent-iad3-2.cdninstagram.com&_nc_cat=103&_nc_oc=Q6cZ2QEXe0vNxFhpDzngf_bNlkpKqkFkdhkZsHhA51T4qyWBbMNKzC7Uf-JVU4i6wCypxkA&_nc_ohc=NSO3tHIU_GIQ7kNvwGAKfhm&_nc_gid=sYR9JFjAApnUbkfBNNVK_A&edm=AOQ1c0wBAAAA&ccb=7-5&oh=00_AfXndhh-MSMqT-zgdY5iUt6gllIVaGA3DE7UXbKXWdAnjA&oe=68A9586D&_nc_sid=8b3546",
        "owner": {
          "id": "17535406778",
          "username": "ur.anuska_02"
        },
        "is_video": false,
        "comment": 0,
        "likes": 0,
        "preview_likes": 0,
        "thumbnail": "https://scontent-iad3-2.cdninstagram.com/v/t51.2885-15/67847246_149991529415619_56392095866175809_n.jpg?stp=dst-jpg_e35_s640x640_sh0.08_tt6&_nc_ht=scontent-iad3-2.cdninstagram.com&_nc_cat=103&_nc_oc=Q6cZ2QEXe0vNxFhpDzngf_bNlkpKqkFkdhkZsHhA51T4qyWBbMNKzC7Uf-JVU4i6wCypxkA&_nc_ohc=NSO3tHIU_GIQ7kNvwGAKfhm&_nc_gid=sYR9JFjAApnUbkfBNNVK_A&edm=AOQ1c0wBAAAA&ccb=7-5&oh=00_AfUG187XWoz9WMoT4Hyl9ihf7OIpSy74koj9LNx61w0YIg&oe=68A9586D&_nc_sid=8b3546",
        "timestamp": 1564777666
      },
      {
        "id": "2101829779551683216",
        "shortcode": "B0rMwxshAKQ",
        "display_url": "https://scontent-iad3-1.cdninstagram.com/v/t51.2885-15/67485071_2329141104040274_4321456994697482011_n.jpg?stp=dst-jpg_e35_tt6&_nc_ht=scontent-iad3-1.cdninstagram.com&_nc_cat=102&_nc_oc=Q6cZ2QEXe0vNxFhpDzngf_bNlkpKqkFkdhkZsHhA51T4qyWBbMNKzC7Uf-JVU4i6wCypxkA&_nc_ohc=OxsCdvBjxVEQ7kNvwG_Nwk7&_nc_gid=sYR9JFjAApnUbkfBNNVK_A&edm=AOQ1c0wBAAAA&ccb=7-5&oh=00_AfVvAfwX18ynQ3u9oQFJwvczhZOtgFZ3RvQU-4EMXc4cxw&oe=68A95BA1&_nc_sid=8b3546",
        "owner": {
          "id": "17535406778",
          "username": "ur.anuska_02"
        },
        "is_video": false,
        "comment": 0,
        "likes": 0,
        "preview_likes": 0,
        "thumbnail": "https://scontent-iad3-1.cdninstagram.com/v/t51.2885-15/67485071_2329141104040274_4321456994697482011_n.jpg?stp=dst-jpg_e35_s640x640_sh0.08_tt6&_nc_ht=scontent-iad3-1.cdninstagram.com&_nc_cat=102&_nc_oc=Q6cZ2QEXe0vNxFhpDzngf_bNlkpKqkFkdhkZsHhA51T4qyWBbMNKzC7Uf-JVU4i6wCypxkA&_nc_ohc=OxsCdvBjxVEQ7kNvwG_Nwk7&_nc_gid=sYR9JFjAApnUbkfBNNVK_A&edm=AOQ1c0wBAAAA&ccb=7-5&oh=00_AfU03epUuNfFCplLhrFgYm9LrfP_9pVgn5lQ8tLp4Ho76Q&oe=68A95BA1&_nc_sid=8b3546",
        "timestamp": 1564777656
      },
      {
        "id": "2101827884112288928",
        "shortcode": "B0rMVMbhhyg",
        "display_url": "https://scontent-iad3-2.cdninstagram.com/v/t51.2885-15/66694437_348656646047922_1924586644645905610_n.jpg?stp=dst-jpg_e35_tt6&_nc_ht=scontent-iad3-2.cdninstagram.com&_nc_cat=106&_nc_oc=Q6cZ2QEXe0vNxFhpDzngf_bNlkpKqkFkdhkZsHhA51T4qyWBbMNKzC7Uf-JVU4i6wCypxkA&_nc_ohc=MJsf_DKeN2EQ7kNvwHZuTga&_nc_gid=sYR9JFjAApnUbkfBNNVK_A&edm=AOQ1c0wBAAAA&ccb=7-5&oh=00_AfXpUkQ_FFfC-BiBuUg3BDfNIyKkgDSwB1esJDjG8e61ww&oe=68A95D7C&_nc_sid=8b3546",
        "owner": {
          "id": "17535406778",
          "username": "ur.anuska_02"
        },
        "is_video": false,
        "comment": 0,
        "likes": 0,
        "preview_likes": 0,
        "thumbnail": "https://scontent-iad3-2.cdninstagram.com/v/t51.2885-15/66694437_348656646047922_1924586644645905610_n.jpg?stp=dst-jpg_e35_s640x640_sh0.08_tt6&_nc_ht=scontent-iad3-2.cdninstagram.com&_nc_cat=106&_nc_oc=Q6cZ2QEXe0vNxFhpDzngf_bNlkpKqkFkdhkZsHhA51T4qyWBbMNKzC7Uf-JVU4i6wCypxkA&_nc_ohc=MJsf_DKeN2EQ7kNvwHZuTga&_nc_gid=sYR9JFjAApnUbkfBNNVK_A&edm=AOQ1c0wBAAAA&ccb=7-5&oh=00_AfWrpGwA0PHbpbRN81dF4vp_mqPDqILDnLV5251f1HUm9g&oe=68A95D7C&_nc_sid=8b3546",
        "timestamp": 1564777430
      },
      {
        "id": "2101827726095996665",
        "shortcode": "B0rMS5RBNb5",
        "display_url": "https://scontent-iad3-1.cdninstagram.com/v/t51.2885-15/67503598_664527857354786_3255064770992303428_n.jpg?stp=dst-jpg_e35_tt6&_nc_ht=scontent-iad3-1.cdninstagram.com&_nc_cat=102&_nc_oc=Q6cZ2QEXe0vNxFhpDzngf_bNlkpKqkFkdhkZsHhA51T4qyWBbMNKzC7Uf-JVU4i6wCypxkA&_nc_ohc=SrMQGq0q0ycQ7kNvwHmy_iV&_nc_gid=sYR9JFjAApnUbkfBNNVK_A&edm=AOQ1c0wBAAAA&ccb=7-5&oh=00_AfXzvcLtOs94oGGUuxB0uBQSXW_z7ILGecncEaMscB0csQ&oe=68A95C56&_nc_sid=8b3546",
        "owner": {
          "id": "17535406778",
          "username": "ur.anuska_02"
        },
        "is_video": false,
        "comment": 0,
        "likes": 0,
        "preview_likes": 0,
        "thumbnail": "https://scontent-iad3-1.cdninstagram.com/v/t51.2885-15/67503598_664527857354786_3255064770992303428_n.jpg?stp=dst-jpg_e35_s640x640_sh0.08_tt6&_nc_ht=scontent-iad3-1.cdninstagram.com&_nc_cat=102&_nc_oc=Q6cZ2QEXe0vNxFhpDzngf_bNlkpKqkFkdhkZsHhA51T4qyWBbMNKzC7Uf-JVU4i6wCypxkA&_nc_ohc=SrMQGq0q0ycQ7kNvwHmy_iV&_nc_gid=sYR9JFjAApnUbkfBNNVK_A&edm=AOQ1c0wBAAAA&ccb=7-5&oh=00_AfXFpG9GxQCwWlJRSW1nJ6zHD3OL_i7DNgw_WmOSw_GItw&oe=68A95C56&_nc_sid=8b3546",
        "timestamp": 1564777411
      },
      {
        "id": "2101827556511887249",
        "shortcode": "B0rMQbVBK-R",
        "display_url": "https://scontent-iad3-2.cdninstagram.com/v/t51.2885-15/66074506_131665628081058_5184882654005628232_n.jpg?stp=dst-jpg_e35_tt6&_nc_ht=scontent-iad3-2.cdninstagram.com&_nc_cat=106&_nc_oc=Q6cZ2QEXe0vNxFhpDzngf_bNlkpKqkFkdhkZsHhA51T4qyWBbMNKzC7Uf-JVU4i6wCypxkA&_nc_ohc=u-sTQNBDiK8Q7kNvwE6GeZl&_nc_gid=sYR9JFjAApnUbkfBNNVK_A&edm=AOQ1c0wBAAAA&ccb=7-5&oh=00_AfXUg92tp0WXc3fBt6YolTT_qWYmWk0RE1Tkvjp7IYbTXw&oe=68A94551&_nc_sid=8b3546",
        "owner": {
          "id": "17535406778",
          "username": "ur.anuska_02"
        },
        "is_video": false,
        "comment": 0,
        "likes": 1,
        "preview_likes": 1,
        "thumbnail": "https://scontent-iad3-2.cdninstagram.com/v/t51.2885-15/66074506_131665628081058_5184882654005628232_n.jpg?stp=dst-jpg_e35_s640x640_sh0.08_tt6&_nc_ht=scontent-iad3-2.cdninstagram.com&_nc_cat=106&_nc_oc=Q6cZ2QEXe0vNxFhpDzngf_bNlkpKqkFkdhkZsHhA51T4qyWBbMNKzC7Uf-JVU4i6wCypxkA&_nc_ohc=u-sTQNBDiK8Q7kNvwE6GeZl&_nc_gid=sYR9JFjAApnUbkfBNNVK_A&edm=AOQ1c0wBAAAA&ccb=7-5&oh=00_AfXUVttXpckUAtRgoDHn00M-eugRLdQ1CDQ3z-sbFnUuTA&oe=68A94551&_nc_sid=8b3546",
        "timestamp": 1564777391
      },
      {
        "id": "2101827466292525326",
        "shortcode": "B0rMPHThnkO",
        "display_url": "https://scontent-iad3-1.cdninstagram.com/v/t51.2885-15/67169299_740067496412564_4825296188352906292_n.jpg?stp=dst-jpg_e35_tt6&_nc_ht=scontent-iad3-1.cdninstagram.com&_nc_cat=108&_nc_oc=Q6cZ2QEXe0vNxFhpDzngf_bNlkpKqkFkdhkZsHhA51T4qyWBbMNKzC7Uf-JVU4i6wCypxkA&_nc_ohc=onVse0IOti4Q7kNvwHgLvub&_nc_gid=sYR9JFjAApnUbkfBNNVK_A&edm=AOQ1c0wBAAAA&ccb=7-5&oh=00_AfUbfI8L7zRGVb40hwhtmz-cwiWIIxoow-tQnhBa6wR3Jg&oe=68A93EC0&_nc_sid=8b3546",
        "owner": {
          "id": "17535406778",
          "username": "ur.anuska_02"
        },
        "is_video": false,
        "comment": 0,
        "likes": 0,
        "preview_likes": 0,
        "thumbnail": "https://scontent-iad3-1.cdninstagram.com/v/t51.2885-15/67169299_740067496412564_4825296188352906292_n.jpg?stp=dst-jpg_e35_s640x640_sh0.08_tt6&_nc_ht=scontent-iad3-1.cdninstagram.com&_nc_cat=108&_nc_oc=Q6cZ2QEXe0vNxFhpDzngf_bNlkpKqkFkdhkZsHhA51T4qyWBbMNKzC7Uf-JVU4i6wCypxkA&_nc_ohc=onVse0IOti4Q7kNvwHgLvub&_nc_gid=sYR9JFjAApnUbkfBNNVK_A&edm=AOQ1c0wBAAAA&ccb=7-5&oh=00_AfVhh8j3jvgKGkz15UFuB6NpC9e5Q6cMN3bPqR3PyDhGjg&oe=68A93EC0&_nc_sid=8b3546",
        "timestamp": 1564777380
      }
    ]
  },
  "account_label": "fake"
}